[
  {"title":"BBC","subtitle":"Staff","ranges":[80],"measures":[28],"markers":[40]},  
  {"title":"NYT","subtitle":"Staff","ranges":[813],"measures":[372],"markers":[406.5]},
  {"title":"Chicago Tribune","subtitle":"Staff","ranges":[200],"measures":[91],"markers":[100]},
  {"title":"Seattles Times","subtitle":"Staff","ranges":[121],"measures":[60],"markers":[60.5]},
  {"title":"Politco","subtitle":"Staff","ranges":[151],"measures":[86],"markers":[75.5]},
  {"title":"NPR","subtitle":"Staff","ranges":[344],"measures":[204],"markers":[172]}
]

